TPCDS_PySpark-1.0.5.data/scripts/tpcds_pyspark_run.py
tpcds_pyspark/__init__.py
tpcds_pyspark/spark-measure_2.12-0.23.jar
tpcds_pyspark/spark-measure_2.12-0.24.jar
tpcds_pyspark/tpcds.py
tpcds_pyspark/tpcds_pyspark_run.py
tpcds_pyspark/Queries/README.txt
tpcds_pyspark/Queries/q1.sql
tpcds_pyspark/Queries/q10.sql
tpcds_pyspark/Queries/q10a.sql
tpcds_pyspark/Queries/q11.sql
tpcds_pyspark/Queries/q12.sql
tpcds_pyspark/Queries/q13.sql
tpcds_pyspark/Queries/q14.sql
tpcds_pyspark/Queries/q14a.sql
tpcds_pyspark/Queries/q14b.sql
tpcds_pyspark/Queries/q15.sql
tpcds_pyspark/Queries/q16.sql
tpcds_pyspark/Queries/q17.sql
tpcds_pyspark/Queries/q18.sql
tpcds_pyspark/Queries/q18a.sql
tpcds_pyspark/Queries/q19.sql
tpcds_pyspark/Queries/q2.sql
tpcds_pyspark/Queries/q20.sql
tpcds_pyspark/Queries/q21.sql
tpcds_pyspark/Queries/q22.sql
tpcds_pyspark/Queries/q22a.sql
tpcds_pyspark/Queries/q23a.sql
tpcds_pyspark/Queries/q23b.sql
tpcds_pyspark/Queries/q24.sql
tpcds_pyspark/Queries/q24a.sql
tpcds_pyspark/Queries/q24b.sql
tpcds_pyspark/Queries/q25.sql
tpcds_pyspark/Queries/q26.sql
tpcds_pyspark/Queries/q27.sql
tpcds_pyspark/Queries/q27a.sql
tpcds_pyspark/Queries/q28.sql
tpcds_pyspark/Queries/q29.sql
tpcds_pyspark/Queries/q3.sql
tpcds_pyspark/Queries/q30.sql
tpcds_pyspark/Queries/q31.sql
tpcds_pyspark/Queries/q32.sql
tpcds_pyspark/Queries/q33.sql
tpcds_pyspark/Queries/q34.sql
tpcds_pyspark/Queries/q35.sql
tpcds_pyspark/Queries/q35a.sql
tpcds_pyspark/Queries/q36.sql
tpcds_pyspark/Queries/q36a.sql
tpcds_pyspark/Queries/q37.sql
tpcds_pyspark/Queries/q38.sql
tpcds_pyspark/Queries/q39a.sql
tpcds_pyspark/Queries/q39b.sql
tpcds_pyspark/Queries/q4.sql
tpcds_pyspark/Queries/q40.sql
tpcds_pyspark/Queries/q41.sql
tpcds_pyspark/Queries/q42.sql
tpcds_pyspark/Queries/q43.sql
tpcds_pyspark/Queries/q44.sql
tpcds_pyspark/Queries/q45.sql
tpcds_pyspark/Queries/q46.sql
tpcds_pyspark/Queries/q47.sql
tpcds_pyspark/Queries/q48.sql
tpcds_pyspark/Queries/q49.sql
tpcds_pyspark/Queries/q5.sql
TPCDS_PySpark-1.0.5.dist-info/LICENSE
TPCDS_PySpark-1.0.5.dist-info/METADATA
TPCDS_PySpark-1.0.5.dist-info/WHEEL
TPCDS_PySpark-1.0.5.dist-info/top_level.txt
TPCDS_PySpark-1.0.5.dist-info/RECORD
