Metadata-Version: 2.1
Name: TPCDS-PySpark
Version: 1.0.5
Summary: TPCDS_PySpark is a TPC-DS workload generator implemented in Python designed to run at scale using Apache Spark.
Home-page: https://github.com/LucaCanali/Miscellaneous/tree/master/Performance_Testing/TPCDS_PySpark
Author: Luca Canali
Author-email: luca.canali@cern.ch
License: Apache License, Version 2.0
Classifier: Programming Language :: Python :: 3
Classifier: Operating System :: OS Independent
Classifier: License :: OSI Approved :: Apache Software License
Classifier: Intended Audience :: Developers
Classifier: Intended Audience :: System Administrators
Classifier: Intended Audience :: Education
Classifier: Development Status :: 4 - Beta
Requires-Python: >=3.9
License-File: LICENSE
